zpic/__init__.py
zpic/contrib/__init__.py
zpic/contrib/em2d_rr.cpython-310-x86_64-linux-gnu.so
zpic/em1d.cpython-310-x86_64-linux-gnu.so
zpic/em1ds.cpython-310-x86_64-linux-gnu.so
zpic/em2d.cpython-310-x86_64-linux-gnu.so
zpic/em2ds.cpython-310-x86_64-linux-gnu.so
zpic/es1d.cpython-310-x86_64-linux-gnu.so
zpic/zdf.py
zpic-0.1.2.dist-info/LICENCE
zpic-0.1.2.dist-info/METADATA
zpic-0.1.2.dist-info/WHEEL
zpic-0.1.2.dist-info/RECORD
