Metadata-Version: 2.3
Name: zpic
Version: 0.1.2
Summary: A fork of the https://github.com/zpic-plasma/zpic project which attempts to integrate the python functionality as a standalone pip package for convenience
Author: Ricardo Teixeira
Author-email: ricardo.a.teixeira@tecnico.ulisboa.pt
Requires-Python: >=3.10
Classifier: Programming Language :: Python :: 3
Classifier: Programming Language :: Python :: 3.10
Classifier: Programming Language :: Python :: 3.11
Classifier: Programming Language :: Python :: 3.12
Classifier: Programming Language :: Python :: 3.13
Requires-Dist: ipympl (>=0.9.7,<0.10.0)
Requires-Dist: ipython (>=8.37.0)
Requires-Dist: jinja2 (>=3.1.6,<4.0.0)
Requires-Dist: jupyterlab (>=4.4.7,<5.0.0)
Requires-Dist: matplotlib (>=3.10.6,<4.0.0)
Requires-Dist: scipy (>=1.15.3)
